pydf_invoice/__init__.py
pydf_invoice/enums.py
pydf_invoice/models.py
pydf_invoice/pdf_invoice.py
pydf_invoice-0.1b0.dist-info/LICENSE
pydf_invoice-0.1b0.dist-info/METADATA
pydf_invoice-0.1b0.dist-info/WHEEL
pydf_invoice-0.1b0.dist-info/top_level.txt
pydf_invoice-0.1b0.dist-info/RECORD
