Metadata-Version: 2.1
Name: pydf-invoice
Version: 0.1b0
Summary: pydf_invoice is a utility class to help developers create PDF invoices using Python easily.
Author-email: Wassim CHAGUETMI <wassim.chaguetmi@gmail.com>
License: GNU GENERAL PUBLIC LICENSE
Project-URL: Homepage, https://github.com/Simouche/pydf_invoice
Project-URL: Bug Tracker, https://github.com/Simouche/pydf_invoice/issues
Classifier: Programming Language :: Python :: 3
Classifier: License :: OSI Approved :: MIT License
Classifier: Operating System :: OS Independent
Requires-Python: >=3.7
License-File: LICENSE
